eq1core/__init__.py
eq1core/configure.py
eq1core/coord_utils.py
eq1core/core.py
eq1core/data.py
eq1core/decorators.py
eq1core/dto.py
eq1core/frame_number.py
eq1core/image_utils.py
eq1core/logger.py
eq1core/plugin.py
eq1core/signal.py
eq1core/utils.py
eq1core/dl/__init__.py
eq1core/dl/centernet.py
eq1core/dl/cfa.py
eq1core/dl/classifier.py
eq1core/dl/faster_rcnn_onnx.py
eq1core/dl/onnx.py
eq1core/dl/centernet_lib/architecture.py
eq1core/dl/centernet_lib/inference.py
eq1core/dl/centernet_lib/utils.py
eq1core/domain/domain_structure.md
eq1core/domain/port_contrainer.py
eq1core/domain/entities/__init__.py
eq1core/domain/entities/audit_logs.py
eq1core/domain/entities/camera.py
eq1core/domain/entities/common.py
eq1core/domain/entities/component.py
eq1core/domain/entities/component_result.py
eq1core/domain/entities/engine.py
eq1core/domain/entities/event.py
eq1core/domain/entities/predictor.py
eq1core/domain/entities/product.py
eq1core/domain/entities/product_result.py
eq1core/domain/entities/users.py
eq1core/domain/entities/vision_presets.py
eq1core/domain/ports/__init__.py
eq1core/domain/ports/audit_logs.py
eq1core/domain/ports/camera.py
eq1core/domain/ports/common.py
eq1core/domain/ports/component.py
eq1core/domain/ports/component_result.py
eq1core/domain/ports/engine.py
eq1core/domain/ports/event.py
eq1core/domain/ports/predictor.py
eq1core/domain/ports/product.py
eq1core/domain/ports/product_result.py
eq1core/domain/ports/users.py
eq1core/domain/ports/vision_presets.py
eq1core/domain/services/__init__.py
eq1core/domain/services/core_data_service.py
eq1core/domain/services/setting_data_service.py
eq1core/engines/__init__.py
eq1core/engines/factory.py
eq1core/engines/interface.py
eq1core/engines/sample.py
eq1core/infrastructure/factory.py
eq1core/infrastructure/setting_file_service.py
eq1core/infrastructure/api/services/core_data_service_impl.py
eq1core/infrastructure/db/__init__.py
eq1core/infrastructure/db/mapper.py
eq1core/infrastructure/db/models/__init__.py
eq1_core-0.2.17.dist-info/METADATA
eq1_core-0.2.17.dist-info/WHEEL
eq1_core-0.2.17.dist-info/RECORD
