Metadata-Version: 2.4
Name: eq1-core
Version: 0.2.17
Summary: EQ1 검사 시스템 핵심 라이브러리 - 카메라 제어, 통신, I/O 처리, 딥러닝 추론 기능 제공
Project-URL: Homepage, https://github.com/crefle/eq1-core
Project-URL: Documentation, https://github.com/crefle/eq1-core#readme
Project-URL: Repository, https://github.com/crefle/eq1-core.git
Project-URL: Issues, https://github.com/crefle/eq1-core/issues
Author-email: "CREFLE INC." <dev@crefle.com>
License: MIT
Keywords: camera,deep-learning,industrial,inspection,quality-control,vision
Classifier: Development Status :: 4 - Beta
Classifier: Intended Audience :: Developers
Classifier: License :: OSI Approved :: MIT License
Classifier: Operating System :: OS Independent
Classifier: Programming Language :: Python :: 3
Classifier: Programming Language :: Python :: 3.12
Classifier: Topic :: Scientific/Engineering :: Artificial Intelligence
Classifier: Topic :: Software Development :: Libraries :: Python Modules
Requires-Python: >=3.12
Requires-Dist: onnxruntime>=1.22.1
Requires-Dist: opencv-python>=4.11.0.86
Requires-Dist: passlib>=1.7.4
Requires-Dist: pillow>=10.0.0
Requires-Dist: pymysql>=1.1.1
Requires-Dist: sqlalchemy>=2.0.41
Requires-Dist: torch>=2.0.0
Requires-Dist: torchvision>=0.15.0
Provides-Extra: dev
Requires-Dist: black>=23.0.0; extra == 'dev'
Requires-Dist: flake8>=6.0.0; extra == 'dev'
Requires-Dist: pylint>=2.17.0; extra == 'dev'
Requires-Dist: pytest-cov>=4.0.0; extra == 'dev'
Requires-Dist: pytest>=7.0.0; extra == 'dev'
Provides-Extra: plotting
Requires-Dist: matplotlib<4.0.0,>=3.0.0; extra == 'plotting'
Provides-Extra: test
Requires-Dist: pytest-cov>=4.0.0; extra == 'test'
Requires-Dist: pytest-mock>=3.10.0; extra == 'test'
Requires-Dist: pytest>=7.0.0; extra == 'test'
